typed_sentinels/__init__.py
typed_sentinels/_core.py
typed_sentinels/_core.pyi
typed_sentinels/_exceptions.py
typed_sentinels/py.typed
typed_sentinels-1.1.0.dist-info/WHEEL
typed_sentinels-1.1.0.dist-info/METADATA
typed_sentinels-1.1.0.dist-info/RECORD
