Metadata-Version: 2.3
Name: typed-sentinels
Version: 1.1.0
Summary: Statically-typed sentinel objects with singleton qualities.
Author: Blockmage Developer, Blockmage Ltd
Author-email: Blockmage Developer <opensource+typed-sentinels@blockmage.dev>, Blockmage Ltd <opensource@blockmage.dev>
Maintainer: Blockmage Developer
Maintainer-email: Blockmage Developer <opensource+typed-sentinels@blockmage.dev>
Requires-Python: >=3.9
Project-URL: documentation, https://typed-sentinels.blockmage.dev
Project-URL: repository, https://github.com/blockmage/typed_sentinels
